Workbook
Name aporte: Planilha1!$E$14
Name patrimonio: Planilha1!$E$17
Name qtd_anos: Planilha1!$E$15
Name rend_carteira: Planilha1!$E$10
Name salario: Planilha1!$E$9
Name Sug_investimento: Planilha1!$E$11
Name taxa_mensal: Planilha1!$E$16

Sheet Planilha1
A1: #VALUE!
C8: CONFIGURAÇÕES
C9: Salário | E9: 3300
C10: Rendimento carteira | E10: 0.006
C11: Sugestão de investimento (30%) | E11: =E9*30% -> 990
C13: INVESTIMENTO MENSAL
C14: Quanto investir por mês? | E14: =Sug_investimento -> 990
C15: Por quantos anos? | E15: 5
C16: Taxa de rendimento mensal | E16: 0.0108
C17: Patrimônio acumulado | E17: =FV(taxa_mensal,qtd_anos*12,aporte,)*-1 -> 82965.979
C18: Dividendos Mensais | E18: =patrimonio*taxa_mensal -> 896.03257
C21: CENÁRIOS | E21: DIVIDENDOS
B22: 2 | C22: Em 2 anos | D22: =FV($E$16,B22*12,$E$14)*-1 -> 26958.555 | E22: =D22*rend_carteira -> 161.75133
B23: 5 | C23: Em 5 anos | D23: =FV($E$16,B23*12,$E$14)*-1 -> 82965.979 | E23: =D23*rend_carteira -> 497.79587
B24: 10 | C24: Em 10 anos | D24: =FV($E$16,B24*12,$E$14)*-1 -> 241023.09 | E24: =D24*rend_carteira -> 1446.1385
B25: 20 | C25: Em 20 anos | D25: =FV($E$16,B25*12,$E$14)*-1 -> 1115778.5 | E25: =D25*rend_carteira -> 6694.671
B26: 30 | C26: Em 30 anos | D26: =FV($E$16,B26*12,$E$14)*-1 -> 4290565.8 | E26: =D26*rend_carteira -> 25743.395
C29: PERFIL | E29: Agressivo
C30: VALOR MENSAL DE INVESTIMENTO | E30: =aporte -> 990
C32: TIPO DE FII | D32: PERCENTUAL SUGERIDO | E32: VALOR
C33: PAPEL | D33: =VLOOKUP($E$29&"-"&$C33,'TABELA DE APOIO'!$A:$D,4,FALSE) -> 0.5 | E33: =aporte*D33 -> 495
C34: TIJOLO | D34: =VLOOKUP($E$29&"-"&$C34,'TABELA DE APOIO'!$A:$D,4,FALSE) -> 0.1 | E34: =aporte*D34 -> 99
C35: HIBRIDOS | D35: =VLOOKUP($E$29&"-"&$C35,'TABELA DE APOIO'!$A:$D,4,FALSE) -> 0.05 | E35: =aporte*D35 -> 49.5
C36: FOFs | D36: =VLOOKUP($E$29&"-"&$C36,'TABELA DE APOIO'!$A:$D,4,FALSE) -> 0.05 | E36: =aporte*D36 -> 49.5
C37: DESENVOLVIMENTO | D37: =VLOOKUP($E$29&"-"&$C37,'TABELA DE APOIO'!$A:$D,4,FALSE) -> 0.2 | E37: =aporte*D37 -> 198
C38: HOTELARIA | D38: =VLOOKUP($E$29&"-"&$C38,'TABELA DE APOIO'!$A:$D,4,FALSE) -> 0.1 | E38: =aporte*D38 -> 99

Sheet TABELA DE APOIO
A2: CHAVE ÚNICA | B2: PERFIL | C2: TIPO DE FII | D2: PERCENTUAL
A3: =$B3&"-"&C3 -> Conservador-PAPEL | B3: Conservador | C3: PAPEL | D3: 0.3 | H3: Moderado-TIJOLO | I3: =VLOOKUP(H3,$A:$D,4,FALSE) -> 0.35
A4: =$B4&"-"&C4 -> Conservador-TIJOLO | B4: Conservador | C4: TIJOLO | D4: 0.5
A5: =$B5&"-"&C5 -> Conservador-HIBRIDOS | B5: Conservador | C5: HIBRIDOS | D5: 0.1
A6: =$B6&"-"&C6 -> Conservador-FOFs | B6: Conservador | C6: FOFs | D6: 0.1
A7: =$B7&"-"&C7 -> Conservador-DESENVOLVIMENTO | B7: Conservador | C7: DESENVOLVIMENTO | D7: 0
A8: =$B8&"-"&C8 -> Conservador-HOTELARIA | B8: Conservador | C8: HOTELARIA | D8: 0
A9: =$B9&"-"&C9 -> Moderado-PAPEL | B9: Moderado | C9: PAPEL | D9: 0.32
A10: =$B10&"-"&C10 -> Moderado-TIJOLO | B10: Moderado | C10: TIJOLO | D10: 0.35
A11: =$B11&"-"&C11 -> Moderado-HIBRIDOS | B11: Moderado | C11: HIBRIDOS | D11: 0.08
A12: =$B12&"-"&C12 -> Moderado-FOFs | B12: Moderado | C12: FOFs | D12: 0.05
A13: =$B13&"-"&C13 -> Moderado-DESENVOLVIMENTO | B13: Moderado | C13: DESENVOLVIMENTO | D13: 0.1
A14: =$B14&"-"&C14 -> Moderado-HOTELARIA | B14: Moderado | C14: HOTELARIA | D14: 0.1
A15: =$B15&"-"&C15 -> Agressivo-PAPEL | B15: Agressivo | C15: PAPEL | D15: 0.5
... A20: =$B20&"-"&C20 -> Agressivo-HOTELARIA | B20: Agressivo | C20: HOTELARIA | D20: 0.1
